tinc/__init__.py
tinc/cachemanager.py
tinc/client.py
tinc/datapool.py
tinc/disk_buffer.py
tinc/distributed_path.py
tinc/message.py
tinc/parameter.py
tinc/parameter_server.py
tinc/parameter_space.py
tinc/parameter_space_tools.py
tinc/preset_handler.py
tinc/process_args.py
tinc/processor.py
tinc/tinc_bridge.py
tinc/tinc_cache_schema.json
tinc/tinc_client.py
tinc/tinc_object.py
tinc/tinc_protocol_pb2.py
tinc/tinc_server.py
tinc/utils.py
tinc/variant.py
tinc-0.9.56.dist-info/LICENSE
tinc-0.9.56.dist-info/METADATA
tinc-0.9.56.dist-info/WHEEL
tinc-0.9.56.dist-info/top_level.txt
tinc-0.9.56.dist-info/RECORD
